[{"Id":0,"Name":"Bl\u00E5malet","Order":1,"ImageUrl":"https://via.placeholder.com/600x400","Description":"Bl\u00E5malet Stel","CategoryId":0,"Category":null},{"Id":1,"Name":"Empire","Order":2,"ImageUrl":"https://via.placeholder.com/600x400","Description":"Empire Stel","CategoryId":0,"Category":null},{"Id":2,"Name":"Fiskestel","Order":3,"ImageUrl":"https://via.placeholder.com/600x400","Description":"Fiskestel","CategoryId":0,"Category":null},{"Id":3,"Name":"Flora Danica","Order":4,"ImageUrl":"https://via.placeholder.com/600x400","Description":"Flora Danica Stel","CategoryId":0,"Category":null},{"Id":4,"Name":"Gr\u00F8n Blomst Svejfet","Order":5,"ImageUrl":"https://via.placeholder.com/600x400","Description":"Gr\u00F8n Blomst Svejfet Stel","CategoryId":0,"Category":null},{"Id":5,"Name":"Guld Vifte","Order":6,"ImageUrl":"https://via.placeholder.com/600x400","Description":"Guld Vifte Stel","CategoryId":0,"Category":null},{"Id":6,"Name":"Henriette","Order":7,"ImageUrl":"https://via.placeholder.com/600x400","Description":"Henriette Stel","CategoryId":0,"Category":null},{"Id":7,"Name":"Konkylie Hvid","Order":8,"ImageUrl":"https://via.placeholder.com/600x400","Description":"Konkylie Hvid Stel","CategoryId":0,"Category":null},{"Id":8,"Name":"Konkylie Rosa","Order":9,"ImageUrl":"https://via.placeholder.com/600x400","Description":"Konkylie Rosa Stel","CategoryId":0,"Category":null},{"Id":9,"Name":"Mega Bl\u00E5","Order":10,"ImageUrl":"https://via.placeholder.com/600x400","Description":"Mega Bl\u00E5 Stel","CategoryId":0,"Category":null},{"Id":10,"Name":"Musselmalet","Order":11,"ImageUrl":"https://via.placeholder.com/600x400","Description":"Musselmalet Stel","CategoryId":0,"Category":null},{"Id":11,"Name":"Bj\u00F8rne","Order":1,"ImageUrl":"https://via.placeholder.com/600x400","Description":"Bj\u00F8rne Figurer","CategoryId":1,"Category":null},{"Id":12,"Name":"Fugle","Order":2,"ImageUrl":"https://via.placeholder.com/600x400","Description":"Fugle Figurer","CategoryId":1,"Category":null},{"Id":13,"Name":"Hunde","Order":3,"ImageUrl":"https://via.placeholder.com/600x400","Description":"Hunde Figurer","CategoryId":1,"Category":null},{"Id":14,"Name":"Kat","Order":4,"ImageUrl":"https://via.placeholder.com/600x400","Description":"Kat Figurer","CategoryId":1,"Category":null},{"Id":15,"Name":"M\u00E6nd og kvinder","Order":5,"ImageUrl":"https://via.placeholder.com/600x400","Description":"M\u00E6nd og kvinder Figurer","CategoryId":1,"Category":null},{"Id":16,"Name":"Mus","Order":6,"ImageUrl":"https://via.placeholder.com/600x400","Description":"Mus Figurer","CategoryId":1,"Category":null},{"Id":17,"Name":"Nisser","Order":7,"ImageUrl":"https://via.placeholder.com/600x400","Description":"Nisser Figurer","CategoryId":1,"Category":null},{"Id":18,"Name":"Papeg\u00F8jer","Order":8,"ImageUrl":"https://via.placeholder.com/600x400","Description":"Papeg\u00F8jer Figurer","CategoryId":1,"Category":null},{"Id":19,"Name":"Pattedyr","Order":9,"ImageUrl":"https://via.placeholder.com/600x400","Description":"Pattedyr Figurer","CategoryId":1,"Category":null},{"Id":20,"Name":"Piger","Order":10,"ImageUrl":"https://via.placeholder.com/600x400","Description":"Piger Figurer","CategoryId":1,"Category":null},{"Id":21,"Name":"Skildpadder","Order":11,"ImageUrl":"https://via.placeholder.com/600x400","Description":"Skildpadder Figurer","CategoryId":1,"Category":null},{"Id":22,"Name":"Aluminia","Order":1,"ImageUrl":"https://via.placeholder.com/600x400","Description":"Aluminia Vaser","CategoryId":2,"Category":null},{"Id":23,"Name":"Baca","Order":2,"ImageUrl":"https://via.placeholder.com/600x400","Description":"Baca Vaser","CategoryId":2,"Category":null},{"Id":24,"Name":"Cylinder","Order":3,"ImageUrl":"https://via.placeholder.com/600x400","Description":"Cylinder Vaser","CategoryId":2,"Category":null},{"Id":25,"Name":"Eva","Order":4,"ImageUrl":"https://via.placeholder.com/600x400","Description":"Eva Vaser","CategoryId":2,"Category":null},{"Id":26,"Name":"Jens Harald Quistgaard","Order":5,"ImageUrl":"https://via.placeholder.com/600x400","Description":"Jens Harald Quistgaard Vaser","CategoryId":2,"Category":null},{"Id":27,"Name":"Kunstfajance","Order":6,"ImageUrl":"https://via.placeholder.com/600x400","Description":"Kunstfajance Vaser","CategoryId":2,"Category":null},{"Id":28,"Name":"Armb\u00E5nd","Order":1,"ImageUrl":"https://via.placeholder.com/600x400","Description":"Armb\u00E5nd Smykker","CategoryId":3,"Category":null},{"Id":29,"Name":"Halsk\u00E6der","Order":2,"ImageUrl":"https://via.placeholder.com/600x400","Description":"Halsk\u00E6der Smykker","CategoryId":3,"Category":null},{"Id":30,"Name":"\u00D8reringe","Order":3,"ImageUrl":"https://via.placeholder.com/600x400","Description":"\u00D8reringe Smykker","CategoryId":3,"Category":null},{"Id":31,"Name":"Ringe","Order":4,"ImageUrl":"https://via.placeholder.com/600x400","Description":"Ringe Smykker","CategoryId":3,"Category":null},{"Id":32,"Name":"Brocher","Order":5,"ImageUrl":"https://via.placeholder.com/600x400","Description":"Brocher Smykker","CategoryId":3,"Category":null},{"Id":42,"Name":"bestik","Order":1,"ImageUrl":"https://via.placeholder.com/600x400","Description":"bestik Smykker","CategoryId":5,"Category":null},{"Id":43,"Name":"Julebestik","Order":2,"ImageUrl":"https://via.placeholder.com/600x400","Description":"Julebestik Smykker","CategoryId":5,"Category":null},{"Id":44,"Name":"Mindebestik","Order":3,"ImageUrl":"https://via.placeholder.com/600x400","Description":"Mindebestik Smykker","CategoryId":5,"Category":null},{"Id":45,"Name":"Andre bestik","Order":4,"ImageUrl":"https://via.placeholder.com/600x400","Description":"Andre bestik Smykker","CategoryId":5,"Category":null},{"Id":46,"Name":"Bj\u00F8rn Wiinblad","Order":1,"ImageUrl":"https://via.placeholder.com/600x400","Description":"Bj\u00F8rn Wiinblad Keramik","CategoryId":6,"Category":null},{"Id":47,"Name":"Ipsen","Order":2,"ImageUrl":"https://via.placeholder.com/600x400","Description":"Ipsen Keramik","CategoryId":6,"Category":null},{"Id":48,"Name":"K\u00E4hler","Order":3,"ImageUrl":"https://via.placeholder.com/600x400","Description":"K\u00E4hler Keramik","CategoryId":6,"Category":null},{"Id":49,"Name":"Saxbo","Order":4,"ImageUrl":"https://via.placeholder.com/600x400","Description":"Saxbo Keramik","CategoryId":6,"Category":null},{"Id":50,"Name":"Arne bang","Order":5,"ImageUrl":"https://via.placeholder.com/600x400","Description":"Arne bang Keramik","CategoryId":6,"Category":null},{"Id":51,"Name":"Palshus","Order":6,"ImageUrl":"https://via.placeholder.com/600x400","Description":"Palshus Keramik","CategoryId":6,"Category":null},{"Id":52,"Name":"Platter","Order":1,"ImageUrl":"https://via.placeholder.com/600x400","Description":"Platter Platter|Plaques","CategoryId":7,"Category":null},{"Id":53,"Name":"\u00C5rskrus","Order":2,"ImageUrl":"https://via.placeholder.com/600x400","Description":"\u00C5rskrus Platter|Plaques","CategoryId":7,"Category":null},{"Id":54,"Name":"Moderne malerier","Order":1,"ImageUrl":"https://via.placeholder.com/600x400","Description":"Moderne malerier Malerier|Paintings","CategoryId":8,"Category":null},{"Id":55,"Name":"\u00C6ldre malerier","Order":2,"ImageUrl":"https://via.placeholder.com/600x400","Description":"\u00C6ldre malerier Malerier|Paintings","CategoryId":8,"Category":null},{"Id":56,"Name":"Loftslamper","Order":1,"ImageUrl":"https://via.placeholder.com/600x400","Description":"Loftslamper Antik og Kunst","CategoryId":9,"Category":null},{"Id":57,"Name":"Bordlamper","Order":2,"ImageUrl":"https://via.placeholder.com/600x400","Description":"Bordlamper Antik og Kunst","CategoryId":9,"Category":null},{"Id":58,"Name":"V\u00E6glamper","Order":3,"ImageUrl":"https://via.placeholder.com/600x400","Description":"V\u00E6glamper Antik og Kunst","CategoryId":9,"Category":null},{"Id":59,"Name":"Standere","Order":4,"ImageUrl":"https://via.placeholder.com/600x400","Description":"Standere Antik og Kunst","CategoryId":9,"Category":null},{"Id":60,"Name":"Andet","Order":5,"ImageUrl":"https://via.placeholder.com/600x400","Description":"Andet Antik og Kunst","CategoryId":9,"Category":null},{"Id":61,"Name":"Vaser","Order":1,"ImageUrl":"https://via.placeholder.com/600x400","Description":"Vaser Antik og Kunst","CategoryId":10,"Category":null},{"Id":62,"Name":"Sk\u00E5le","Order":2,"ImageUrl":"https://via.placeholder.com/600x400","Description":"Sk\u00E5le Antik og Kunst","CategoryId":10,"Category":null},{"Id":63,"Name":"Kander","Order":3,"ImageUrl":"https://via.placeholder.com/600x400","Description":"Kander Antik og Kunst","CategoryId":10,"Category":null},{"Id":64,"Name":"Glasfigurer","Order":4,"ImageUrl":"https://via.placeholder.com/600x400","Description":"Glasfigurer Antik og Kunst","CategoryId":10,"Category":null},{"Id":65,"Name":"Bestik","Order":1,"ImageUrl":"https://via.placeholder.com/600x400","Description":"Bestik forhandlet af S\u00F8lv|Silver","CategoryId":3,"Category":null},{"Id":66,"Name":"Lysestager","Order":2,"ImageUrl":"https://via.placeholder.com/600x400","Description":"Lysestager forhandlet af S\u00F8lv|Silver","CategoryId":3,"Category":null},{"Id":67,"Name":"Fade","Order":3,"ImageUrl":"https://via.placeholder.com/600x400","Description":"Fade forhandlet af S\u00F8lv|Silver","CategoryId":3,"Category":null},{"Id":68,"Name":"Kander","Order":4,"ImageUrl":"https://via.placeholder.com/600x400","Description":"Kander forhandlet af S\u00F8lv|Silver","CategoryId":3,"Category":null},{"Id":69,"Name":"Diverse","Order":5,"ImageUrl":"https://via.placeholder.com/600x400","Description":"Diverse s\u00F8lvting forhandlet af S\u00F8lv|Silver","CategoryId":3,"Category":null},{"Id":70,"Name":"Ringe","Order":2,"ImageUrl":"https://via.placeholder.com/600x400","Description":"Ringe Smykker","CategoryId":4,"Category":null},{"Id":71,"Name":"\u00D8reringe","Order":2,"ImageUrl":"https://via.placeholder.com/600x400","Description":"\u00D8reringe Smykker","CategoryId":4,"Category":null},{"Id":72,"Name":"Armb\u00E5nd","Order":3,"ImageUrl":"https://via.placeholder.com/600x400","Description":"Armb\u00E5nd Smykker","CategoryId":4,"Category":null},{"Id":73,"Name":"Halsk\u00E6der","Order":4,"ImageUrl":"https://via.placeholder.com/600x400","Description":"Halsk\u00E6der Smykker","CategoryId":4,"Category":null},{"Id":74,"Name":"Brocher","Order":5,"ImageUrl":"https://via.placeholder.com/600x400","Description":"Brocher Smykker","CategoryId":4,"Category":null}]